{
  "id": "176",
  "name": "YUKIri",
  "coverUrl": "http://i0.hdslb.com/bfs/emote/06b2faf1cd103472519489e9b8b816d13c9be8b0.png",
  "emojis": [
    {
      "id": "3202",
      "description": "YUKIri_非洲鱼鱼萌",
      "shortCodes": [
        "[YUKIri_非洲鱼鱼萌]"
      ],
      "staticUrl": "assets/bilibili/176/3202.png",
      "isHide": false,
      "packageId": "176",
      "meta": {
        "packageName": "YUKIri",
        "packageCover": "http://i0.hdslb.com/bfs/emote/06b2faf1cd103472519489e9b8b816d13c9be8b0.png",
        "originalUrl": "http://i0.hdslb.com/bfs/emote/f40d6e8a997912fe5eab661f60abb5f4b677e58c.png"
      }
    },
    {
      "id": "3203",
      "description": "YUKIri_好耶",
      "shortCodes": [
        "[YUKIri_好耶]"
      ],
      "staticUrl": "assets/bilibili/176/3203.png",
      "isHide": false,
      "packageId": "176",
      "meta": {
        "packageName": "YUKIri",
        "packageCover": "http://i0.hdslb.com/bfs/emote/06b2faf1cd103472519489e9b8b816d13c9be8b0.png",
        "originalUrl": "http://i0.hdslb.com/bfs/emote/3cc8f404dc3dffc89a2101bbb29d23074bb74d9c.png"
      }
    },
    {
      "id": "3204",
      "description": "YUKIri_很强",
      "shortCodes": [
        "[YUKIri_很强]"
      ],
      "staticUrl": "assets/bilibili/176/3204.png",
      "isHide": false,
      "packageId": "176",
      "meta": {
        "packageName": "YUKIri",
        "packageCover": "http://i0.hdslb.com/bfs/emote/06b2faf1cd103472519489e9b8b816d13c9be8b0.png",
        "originalUrl": "http://i0.hdslb.com/bfs/emote/98defac58f7f324bcae5d7464c70a409147801c6.png"
      }
    },
    {
      "id": "3205",
      "description": "YUKIri_咧嘴笑",
      "shortCodes": [
        "[YUKIri_咧嘴笑]"
      ],
      "staticUrl": "assets/bilibili/176/3205.png",
      "isHide": false,
      "packageId": "176",
      "meta": {
        "packageName": "YUKIri",
        "packageCover": "http://i0.hdslb.com/bfs/emote/06b2faf1cd103472519489e9b8b816d13c9be8b0.png",
        "originalUrl": "http://i0.hdslb.com/bfs/emote/014eed967285ddfad14596fa3bc69db7c630d1a4.png"
      }
    },
    {
      "id": "3206",
      "description": "YUKIri_裂开了",
      "shortCodes": [
        "[YUKIri_裂开了]"
      ],
      "staticUrl": "assets/bilibili/176/3206.png",
      "isHide": false,
      "packageId": "176",
      "meta": {
        "packageName": "YUKIri",
        "packageCover": "http://i0.hdslb.com/bfs/emote/06b2faf1cd103472519489e9b8b816d13c9be8b0.png",
        "originalUrl": "http://i0.hdslb.com/bfs/emote/017e285e2fd6143f772e191bf85e2ec64807bd29.png"
      }
    },
    {
      "id": "3207",
      "description": "YUKIri_摸鱼",
      "shortCodes": [
        "[YUKIri_摸鱼]"
      ],
      "staticUrl": "assets/bilibili/176/3207.png",
      "isHide": false,
      "packageId": "176",
      "meta": {
        "packageName": "YUKIri",
        "packageCover": "http://i0.hdslb.com/bfs/emote/06b2faf1cd103472519489e9b8b816d13c9be8b0.png",
        "originalUrl": "http://i0.hdslb.com/bfs/emote/b167fe49e373b9b1be47d2a75adde3eaa8fa142c.png"
      }
    },
    {
      "id": "3208",
      "description": "YUKIri_鱼鱼大笑",
      "shortCodes": [
        "[YUKIri_鱼鱼大笑]"
      ],
      "staticUrl": "assets/bilibili/176/3208.png",
      "isHide": false,
      "packageId": "176",
      "meta": {
        "packageName": "YUKIri",
        "packageCover": "http://i0.hdslb.com/bfs/emote/06b2faf1cd103472519489e9b8b816d13c9be8b0.png",
        "originalUrl": "http://i0.hdslb.com/bfs/emote/5b3bf3a7f5d030ad3328e7c3b83c9d4d00e05222.png"
      }
    },
    {
      "id": "3209",
      "description": "YUKIri_鱼鱼萌",
      "shortCodes": [
        "[YUKIri_鱼鱼萌]"
      ],
      "staticUrl": "assets/bilibili/176/3209.png",
      "isHide": false,
      "packageId": "176",
      "meta": {
        "packageName": "YUKIri",
        "packageCover": "http://i0.hdslb.com/bfs/emote/06b2faf1cd103472519489e9b8b816d13c9be8b0.png",
        "originalUrl": "http://i0.hdslb.com/bfs/emote/556bc2fd30f2dd264299154b147ec39cb7b6b6d7.png"
      }
    },
    {
      "id": "3210",
      "description": "YUKIri_鱼鱼萌吃惊",
      "shortCodes": [
        "[YUKIri_鱼鱼萌吃惊]"
      ],
      "staticUrl": "assets/bilibili/176/3210.png",
      "isHide": false,
      "packageId": "176",
      "meta": {
        "packageName": "YUKIri",
        "packageCover": "http://i0.hdslb.com/bfs/emote/06b2faf1cd103472519489e9b8b816d13c9be8b0.png",
        "originalUrl": "http://i0.hdslb.com/bfs/emote/7336a3422c04ced070e2145bade91ec3c07e58f4.png"
      }
    },
    {
      "id": "3211",
      "description": "YUKIri_起飞",
      "shortCodes": [
        "[YUKIri_起飞]"
      ],
      "staticUrl": "assets/bilibili/176/3211.png",
      "isHide": false,
      "packageId": "176",
      "meta": {
        "packageName": "YUKIri",
        "packageCover": "http://i0.hdslb.com/bfs/emote/06b2faf1cd103472519489e9b8b816d13c9be8b0.png",
        "originalUrl": "http://i0.hdslb.com/bfs/emote/b2265ddf44971c21bf90fb3e1bb81fbf82e136c8.png"
      }
    },
    {
      "id": "3212",
      "description": "YUKIri_生气",
      "shortCodes": [
        "[YUKIri_生气]"
      ],
      "staticUrl": "assets/bilibili/176/3212.png",
      "isHide": false,
      "packageId": "176",
      "meta": {
        "packageName": "YUKIri",
        "packageCover": "http://i0.hdslb.com/bfs/emote/06b2faf1cd103472519489e9b8b816d13c9be8b0.png",
        "originalUrl": "http://i0.hdslb.com/bfs/emote/21b0ee844a62d1cf8cc62fe09048e15d9fc4fe35.png"
      }
    },
    {
      "id": "3213",
      "description": "YUKIri_委屈",
      "shortCodes": [
        "[YUKIri_委屈]"
      ],
      "staticUrl": "assets/bilibili/176/3213.png",
      "isHide": false,
      "packageId": "176",
      "meta": {
        "packageName": "YUKIri",
        "packageCover": "http://i0.hdslb.com/bfs/emote/06b2faf1cd103472519489e9b8b816d13c9be8b0.png",
        "originalUrl": "http://i0.hdslb.com/bfs/emote/3556fb9581b31979a1b1d6a390c47d4d3cf1872e.png"
      }
    },
    {
      "id": "3214",
      "description": "YUKIri_无奈",
      "shortCodes": [
        "[YUKIri_无奈]"
      ],
      "staticUrl": "assets/bilibili/176/3214.png",
      "isHide": false,
      "packageId": "176",
      "meta": {
        "packageName": "YUKIri",
        "packageCover": "http://i0.hdslb.com/bfs/emote/06b2faf1cd103472519489e9b8b816d13c9be8b0.png",
        "originalUrl": "http://i0.hdslb.com/bfs/emote/3da4e1fd83a9239d79b304988fb0378465390897.png"
      }
    },
    {
      "id": "3215",
      "description": "YUKIri_疑问",
      "shortCodes": [
        "[YUKIri_疑问]"
      ],
      "staticUrl": "assets/bilibili/176/3215.png",
      "isHide": false,
      "packageId": "176",
      "meta": {
        "packageName": "YUKIri",
        "packageCover": "http://i0.hdslb.com/bfs/emote/06b2faf1cd103472519489e9b8b816d13c9be8b0.png",
        "originalUrl": "http://i0.hdslb.com/bfs/emote/790beeba2da48fe94e5232c72973615e61f26f5d.png"
      }
    },
    {
      "id": "3216",
      "description": "YUKIri_哭哭",
      "shortCodes": [
        "[YUKIri_哭哭]"
      ],
      "staticUrl": "assets/bilibili/176/3216.png",
      "isHide": false,
      "packageId": "176",
      "meta": {
        "packageName": "YUKIri",
        "packageCover": "http://i0.hdslb.com/bfs/emote/06b2faf1cd103472519489e9b8b816d13c9be8b0.png",
        "originalUrl": "http://i0.hdslb.com/bfs/emote/c15798103757fdc28db6e6643a114c14544437d4.png"
      }
    }
  ]
}
