{
  "id": "302",
  "name": "恋乃夜舞",
  "coverUrl": "http://i0.hdslb.com/bfs/emote/bbf32a31aa114e0477256a4f936734287e69d124.png",
  "emojis": [
    {
      "id": "4958",
      "description": "恋乃夜舞_kira",
      "shortCodes": [
        "[恋乃夜舞_kira]"
      ],
      "staticUrl": "assets/bilibili/302/4958.png",
      "isHide": false,
      "packageId": "302",
      "meta": {
        "packageName": "恋乃夜舞",
        "packageCover": "http://i0.hdslb.com/bfs/emote/bbf32a31aa114e0477256a4f936734287e69d124.png",
        "originalUrl": "http://i0.hdslb.com/bfs/emote/fb0fbc4245ddc98a40644d3bffc039700d54432e.png"
      }
    },
    {
      "id": "4959",
      "description": "恋乃夜舞_pero",
      "shortCodes": [
        "[恋乃夜舞_pero]"
      ],
      "staticUrl": "assets/bilibili/302/4959.png",
      "isHide": false,
      "packageId": "302",
      "meta": {
        "packageName": "恋乃夜舞",
        "packageCover": "http://i0.hdslb.com/bfs/emote/bbf32a31aa114e0477256a4f936734287e69d124.png",
        "originalUrl": "http://i0.hdslb.com/bfs/emote/54fcaed3e392e40ebd885cd36b0fb3c1b9535bd0.png"
      }
    },
    {
      "id": "4960",
      "description": "恋乃夜舞_yuyuyu",
      "shortCodes": [
        "[恋乃夜舞_yuyuyu]"
      ],
      "staticUrl": "assets/bilibili/302/4960.png",
      "isHide": false,
      "packageId": "302",
      "meta": {
        "packageName": "恋乃夜舞",
        "packageCover": "http://i0.hdslb.com/bfs/emote/bbf32a31aa114e0477256a4f936734287e69d124.png",
        "originalUrl": "http://i0.hdslb.com/bfs/emote/6c88caeb75135e0b8dfab3562eb8249f90159d34.png"
      }
    },
    {
      "id": "4961",
      "description": "恋乃夜舞_感情",
      "shortCodes": [
        "[恋乃夜舞_感情]"
      ],
      "staticUrl": "assets/bilibili/302/4961.png",
      "isHide": false,
      "packageId": "302",
      "meta": {
        "packageName": "恋乃夜舞",
        "packageCover": "http://i0.hdslb.com/bfs/emote/bbf32a31aa114e0477256a4f936734287e69d124.png",
        "originalUrl": "http://i0.hdslb.com/bfs/emote/4c60d41a8f301bd91a409594e132b9e4df603243.png"
      }
    },
    {
      "id": "4962",
      "description": "恋乃夜舞_技巧",
      "shortCodes": [
        "[恋乃夜舞_技巧]"
      ],
      "staticUrl": "assets/bilibili/302/4962.png",
      "isHide": false,
      "packageId": "302",
      "meta": {
        "packageName": "恋乃夜舞",
        "packageCover": "http://i0.hdslb.com/bfs/emote/bbf32a31aa114e0477256a4f936734287e69d124.png",
        "originalUrl": "http://i0.hdslb.com/bfs/emote/54ad8c9f97dfec3e43132a25a6049afa5de529c1.png"
      }
    },
    {
      "id": "4963",
      "description": "恋乃夜舞_干杯",
      "shortCodes": [
        "[恋乃夜舞_干杯]"
      ],
      "staticUrl": "assets/bilibili/302/4963.png",
      "isHide": false,
      "packageId": "302",
      "meta": {
        "packageName": "恋乃夜舞",
        "packageCover": "http://i0.hdslb.com/bfs/emote/bbf32a31aa114e0477256a4f936734287e69d124.png",
        "originalUrl": "http://i0.hdslb.com/bfs/emote/d0da35b616f3aabf02404f6ba465963d79e74a00.png"
      }
    },
    {
      "id": "4964",
      "description": "恋乃夜舞_害怕",
      "shortCodes": [
        "[恋乃夜舞_害怕]"
      ],
      "staticUrl": "assets/bilibili/302/4964.png",
      "isHide": false,
      "packageId": "302",
      "meta": {
        "packageName": "恋乃夜舞",
        "packageCover": "http://i0.hdslb.com/bfs/emote/bbf32a31aa114e0477256a4f936734287e69d124.png",
        "originalUrl": "http://i0.hdslb.com/bfs/emote/8a4498eb65c6acd51e3e504dd008207c60a7908e.png"
      }
    },
    {
      "id": "4965",
      "description": "恋乃夜舞_好耶",
      "shortCodes": [
        "[恋乃夜舞_好耶]"
      ],
      "staticUrl": "assets/bilibili/302/4965.png",
      "isHide": false,
      "packageId": "302",
      "meta": {
        "packageName": "恋乃夜舞",
        "packageCover": "http://i0.hdslb.com/bfs/emote/bbf32a31aa114e0477256a4f936734287e69d124.png",
        "originalUrl": "http://i0.hdslb.com/bfs/emote/4a2a6a4f932287e134bbab27899f8b984417a45b.png"
      }
    },
    {
      "id": "4966",
      "description": "恋乃夜舞_哭",
      "shortCodes": [
        "[恋乃夜舞_哭]"
      ],
      "staticUrl": "assets/bilibili/302/4966.png",
      "isHide": false,
      "packageId": "302",
      "meta": {
        "packageName": "恋乃夜舞",
        "packageCover": "http://i0.hdslb.com/bfs/emote/bbf32a31aa114e0477256a4f936734287e69d124.png",
        "originalUrl": "http://i0.hdslb.com/bfs/emote/1aea217a5035b820114bfacd098e6bc964f11b68.png"
      }
    },
    {
      "id": "4967",
      "description": "恋乃夜舞_困",
      "shortCodes": [
        "[恋乃夜舞_困]"
      ],
      "staticUrl": "assets/bilibili/302/4967.png",
      "isHide": false,
      "packageId": "302",
      "meta": {
        "packageName": "恋乃夜舞",
        "packageCover": "http://i0.hdslb.com/bfs/emote/bbf32a31aa114e0477256a4f936734287e69d124.png",
        "originalUrl": "http://i0.hdslb.com/bfs/emote/0a2b12770d2b0ffda95a976337151937e2a3fcd7.png"
      }
    },
    {
      "id": "4968",
      "description": "恋乃夜舞_骂倒",
      "shortCodes": [
        "[恋乃夜舞_骂倒]"
      ],
      "staticUrl": "assets/bilibili/302/4968.png",
      "isHide": false,
      "packageId": "302",
      "meta": {
        "packageName": "恋乃夜舞",
        "packageCover": "http://i0.hdslb.com/bfs/emote/bbf32a31aa114e0477256a4f936734287e69d124.png",
        "originalUrl": "http://i0.hdslb.com/bfs/emote/9a84aa1e5ad0c9493676671a98984e1d6b334e84.png"
      }
    },
    {
      "id": "4969",
      "description": "恋乃夜舞_束缚",
      "shortCodes": [
        "[恋乃夜舞_束缚]"
      ],
      "staticUrl": "assets/bilibili/302/4969.png",
      "isHide": false,
      "packageId": "302",
      "meta": {
        "packageName": "恋乃夜舞",
        "packageCover": "http://i0.hdslb.com/bfs/emote/bbf32a31aa114e0477256a4f936734287e69d124.png",
        "originalUrl": "http://i0.hdslb.com/bfs/emote/b99bb7d0dbc6a2e707046b0c58687c5bc6680945.png"
      }
    },
    {
      "id": "4970",
      "description": "恋乃夜舞_天才",
      "shortCodes": [
        "[恋乃夜舞_天才]"
      ],
      "staticUrl": "assets/bilibili/302/4970.png",
      "isHide": false,
      "packageId": "302",
      "meta": {
        "packageName": "恋乃夜舞",
        "packageCover": "http://i0.hdslb.com/bfs/emote/bbf32a31aa114e0477256a4f936734287e69d124.png",
        "originalUrl": "http://i0.hdslb.com/bfs/emote/594e26c3370ed9de7153485ca1f42d6f4d3ec2bf.png"
      }
    },
    {
      "id": "4971",
      "description": "恋乃夜舞_笑",
      "shortCodes": [
        "[恋乃夜舞_笑]"
      ],
      "staticUrl": "assets/bilibili/302/4971.png",
      "isHide": false,
      "packageId": "302",
      "meta": {
        "packageName": "恋乃夜舞",
        "packageCover": "http://i0.hdslb.com/bfs/emote/bbf32a31aa114e0477256a4f936734287e69d124.png",
        "originalUrl": "http://i0.hdslb.com/bfs/emote/d534776b283c39b4c6e5715f524ee5539833ddf1.png"
      }
    },
    {
      "id": "4972",
      "description": "恋乃夜舞_心",
      "shortCodes": [
        "[恋乃夜舞_心]"
      ],
      "staticUrl": "assets/bilibili/302/4972.png",
      "isHide": false,
      "packageId": "302",
      "meta": {
        "packageName": "恋乃夜舞",
        "packageCover": "http://i0.hdslb.com/bfs/emote/bbf32a31aa114e0477256a4f936734287e69d124.png",
        "originalUrl": "http://i0.hdslb.com/bfs/emote/b9754445ce4415f64b48cc8db22645b28fc79344.png"
      }
    }
  ]
}