{
  "id": "383",
  "name": "时光代理人周年纪念",
  "coverUrl": "http://i0.hdslb.com/bfs/emote/bc6be9a6aabbdc3597e6c480587b75f8ebdb7741.png",
  "emojis": [
    {
      "id": "6346",
      "description": "时光代理人周年纪念_比心",
      "shortCodes": [
        "[时光代理人周年纪念_比心]"
      ],
      "staticUrl": "assets/bilibili/383/6346.png",
      "isHide": false,
      "packageId": "383",
      "meta": {
        "packageName": "时光代理人周年纪念",
        "packageCover": "http://i0.hdslb.com/bfs/emote/bc6be9a6aabbdc3597e6c480587b75f8ebdb7741.png",
        "originalUrl": "http://i0.hdslb.com/bfs/emote/9af6d8310808b5f635b1644cf947b2472854c2d9.png"
      }
    },
    {
      "id": "6347",
      "description": "时光代理人周年纪念_emmm",
      "shortCodes": [
        "[时光代理人周年纪念_emmm]"
      ],
      "staticUrl": "assets/bilibili/383/6347.png",
      "isHide": false,
      "packageId": "383",
      "meta": {
        "packageName": "时光代理人周年纪念",
        "packageCover": "http://i0.hdslb.com/bfs/emote/bc6be9a6aabbdc3597e6c480587b75f8ebdb7741.png",
        "originalUrl": "http://i0.hdslb.com/bfs/emote/7ca9f17f1f8357b6a436570ca24ee1a5aa14176f.png"
      }
    },
    {
      "id": "6348",
      "description": "时光代理人周年纪念_salute",
      "shortCodes": [
        "[时光代理人周年纪念_salute]"
      ],
      "staticUrl": "assets/bilibili/383/6348.png",
      "isHide": false,
      "packageId": "383",
      "meta": {
        "packageName": "时光代理人周年纪念",
        "packageCover": "http://i0.hdslb.com/bfs/emote/bc6be9a6aabbdc3597e6c480587b75f8ebdb7741.png",
        "originalUrl": "http://i0.hdslb.com/bfs/emote/028b9d80e8c1a4edcc3e79bf460ae1fcdf76b26d.png"
      }
    },
    {
      "id": "6349",
      "description": "时光代理人周年纪念_不",
      "shortCodes": [
        "[时光代理人周年纪念_不]"
      ],
      "staticUrl": "assets/bilibili/383/6349.png",
      "isHide": false,
      "packageId": "383",
      "meta": {
        "packageName": "时光代理人周年纪念",
        "packageCover": "http://i0.hdslb.com/bfs/emote/bc6be9a6aabbdc3597e6c480587b75f8ebdb7741.png",
        "originalUrl": "http://i0.hdslb.com/bfs/emote/9e3e5fcd0125a01f5b827fe670a53a9cb16099f7.png"
      }
    },
    {
      "id": "6350",
      "description": "时光代理人周年纪念_钞能力",
      "shortCodes": [
        "[时光代理人周年纪念_钞能力]"
      ],
      "staticUrl": "assets/bilibili/383/6350.png",
      "isHide": false,
      "packageId": "383",
      "meta": {
        "packageName": "时光代理人周年纪念",
        "packageCover": "http://i0.hdslb.com/bfs/emote/bc6be9a6aabbdc3597e6c480587b75f8ebdb7741.png",
        "originalUrl": "http://i0.hdslb.com/bfs/emote/e818350cc7a2d05f75462daab2b9e22d620c958a.png"
      }
    },
    {
      "id": "6351",
      "description": "时光代理人周年纪念_盯",
      "shortCodes": [
        "[时光代理人周年纪念_盯]"
      ],
      "staticUrl": "assets/bilibili/383/6351.png",
      "isHide": false,
      "packageId": "383",
      "meta": {
        "packageName": "时光代理人周年纪念",
        "packageCover": "http://i0.hdslb.com/bfs/emote/bc6be9a6aabbdc3597e6c480587b75f8ebdb7741.png",
        "originalUrl": "http://i0.hdslb.com/bfs/emote/8fca63db5358d77fee0a8bc4548e0db0f1c78a49.png"
      }
    },
    {
      "id": "6352",
      "description": "时光代理人周年纪念_好耶",
      "shortCodes": [
        "[时光代理人周年纪念_好耶]"
      ],
      "staticUrl": "assets/bilibili/383/6352.png",
      "isHide": false,
      "packageId": "383",
      "meta": {
        "packageName": "时光代理人周年纪念",
        "packageCover": "http://i0.hdslb.com/bfs/emote/bc6be9a6aabbdc3597e6c480587b75f8ebdb7741.png",
        "originalUrl": "http://i0.hdslb.com/bfs/emote/9fdeac7a4e517b25030302832306a84f0a8081cf.png"
      }
    },
    {
      "id": "6353",
      "description": "时光代理人周年纪念_酷",
      "shortCodes": [
        "[时光代理人周年纪念_酷]"
      ],
      "staticUrl": "assets/bilibili/383/6353.png",
      "isHide": false,
      "packageId": "383",
      "meta": {
        "packageName": "时光代理人周年纪念",
        "packageCover": "http://i0.hdslb.com/bfs/emote/bc6be9a6aabbdc3597e6c480587b75f8ebdb7741.png",
        "originalUrl": "http://i0.hdslb.com/bfs/emote/c27237bdd4c0c8f4c20d19b5889b5d326c39d625.png"
      }
    },
    {
      "id": "6354",
      "description": "时光代理人周年纪念_买买买",
      "shortCodes": [
        "[时光代理人周年纪念_买买买]"
      ],
      "staticUrl": "assets/bilibili/383/6354.png",
      "isHide": false,
      "packageId": "383",
      "meta": {
        "packageName": "时光代理人周年纪念",
        "packageCover": "http://i0.hdslb.com/bfs/emote/bc6be9a6aabbdc3597e6c480587b75f8ebdb7741.png",
        "originalUrl": "http://i0.hdslb.com/bfs/emote/bb1b075895fe58505586a23fb57aff4ef50c5c43.png"
      }
    },
    {
      "id": "6355",
      "description": "时光代理人周年纪念_你醒啦",
      "shortCodes": [
        "[时光代理人周年纪念_你醒啦]"
      ],
      "staticUrl": "assets/bilibili/383/6355.png",
      "isHide": false,
      "packageId": "383",
      "meta": {
        "packageName": "时光代理人周年纪念",
        "packageCover": "http://i0.hdslb.com/bfs/emote/bc6be9a6aabbdc3597e6c480587b75f8ebdb7741.png",
        "originalUrl": "http://i0.hdslb.com/bfs/emote/7e94f51f7252c7657d98e9d30c67829125385583.png"
      }
    },
    {
      "id": "6356",
      "description": "时光代理人周年纪念_怒",
      "shortCodes": [
        "[时光代理人周年纪念_怒]"
      ],
      "staticUrl": "assets/bilibili/383/6356.png",
      "isHide": false,
      "packageId": "383",
      "meta": {
        "packageName": "时光代理人周年纪念",
        "packageCover": "http://i0.hdslb.com/bfs/emote/bc6be9a6aabbdc3597e6c480587b75f8ebdb7741.png",
        "originalUrl": "http://i0.hdslb.com/bfs/emote/de847eae440ea7bd8cd6642c17507d03e7f2e696.png"
      }
    },
    {
      "id": "6357",
      "description": "时光代理人周年纪念_期待",
      "shortCodes": [
        "[时光代理人周年纪念_期待]"
      ],
      "staticUrl": "assets/bilibili/383/6357.png",
      "isHide": false,
      "packageId": "383",
      "meta": {
        "packageName": "时光代理人周年纪念",
        "packageCover": "http://i0.hdslb.com/bfs/emote/bc6be9a6aabbdc3597e6c480587b75f8ebdb7741.png",
        "originalUrl": "http://i0.hdslb.com/bfs/emote/bc230e2373be0a1826c993d0a781abf8343dd317.png"
      }
    },
    {
      "id": "6358",
      "description": "时光代理人周年纪念_无论过去",
      "shortCodes": [
        "[时光代理人周年纪念_无论过去]"
      ],
      "staticUrl": "assets/bilibili/383/6358.png",
      "isHide": false,
      "packageId": "383",
      "meta": {
        "packageName": "时光代理人周年纪念",
        "packageCover": "http://i0.hdslb.com/bfs/emote/bc6be9a6aabbdc3597e6c480587b75f8ebdb7741.png",
        "originalUrl": "http://i0.hdslb.com/bfs/emote/7a31be18fb120d1ca5a775695007c6af13092b49.png"
      }
    },
    {
      "id": "6359",
      "description": "时光代理人周年纪念_心脏骤停",
      "shortCodes": [
        "[时光代理人周年纪念_心脏骤停]"
      ],
      "staticUrl": "assets/bilibili/383/6359.png",
      "isHide": false,
      "packageId": "383",
      "meta": {
        "packageName": "时光代理人周年纪念",
        "packageCover": "http://i0.hdslb.com/bfs/emote/bc6be9a6aabbdc3597e6c480587b75f8ebdb7741.png",
        "originalUrl": "http://i0.hdslb.com/bfs/emote/dff5c7b544172fd376dd60e351db1394f3e4e32c.png"
      }
    },
    {
      "id": "6360",
      "description": "时光代理人周年纪念_一周年快乐",
      "shortCodes": [
        "[时光代理人周年纪念_一周年快乐]"
      ],
      "staticUrl": "assets/bilibili/383/6360.png",
      "isHide": false,
      "packageId": "383",
      "meta": {
        "packageName": "时光代理人周年纪念",
        "packageCover": "http://i0.hdslb.com/bfs/emote/bc6be9a6aabbdc3597e6c480587b75f8ebdb7741.png",
        "originalUrl": "http://i0.hdslb.com/bfs/emote/1fe94207e8d295e05a5cde6a8a20cd23d6d1cf57.png"
      }
    }
  ]
}
